README.txt
setup.py
bauhattan/__init__.py
bauhattan.egg-info/PKG-INFO
bauhattan.egg-info/SOURCES.txt
bauhattan.egg-info/dependency_links.txt
bauhattan.egg-info/requires.txt
bauhattan.egg-info/top_level.txt
bauhattan/connectors/__init__.py
bauhattan/connectors/maven.py