Metadata-Version: 1.1
Name: bauhattan
Version: 0.1.2
Summary: Automated CI/CD Tool
Home-page: https://github.com/izrik/bauhattan
Author: izrik
Author-email: izrik@yahoo.com
License: MIT License
Platform: UNKNOWN
Classifier: Development Status :: 3 - Alpha
Classifier: Intended Audience :: Developers
Classifier: Natural Language :: English
Classifier: License :: OSI Approved :: MIT License
Classifier: Programming Language :: Python
Classifier: Programming Language :: Python :: 2.7
